aligned/__init__.py
aligned/checks.py
aligned/cli.py
aligned/compiler/aggregation_factory.py
aligned/compiler/feature_factory.py
aligned/compiler/model.py
aligned/compiler/repo_reader.py
aligned/compiler/tests/features.py
aligned/compiler/tests/test_repo_reader.py
aligned/compiler/transformation_factory.py
aligned/compiler/vector_index_factory.py
aligned/config_value.py
aligned/data_file.py
aligned/data_source/__init__.py
aligned/data_source/batch_data_source.py
aligned/data_source/model_predictor.py
aligned/data_source/stream_data_source.py
aligned/data_source/tests/test_batch_source.py
aligned/exceptions.py
aligned/exposed_model/__init__.py
aligned/exposed_model/interface.py
aligned/exposed_model/langchain.py
aligned/exposed_model/langchain_retriever.py
aligned/exposed_model/mlflow.py
aligned/exposed_model/multiple.py
aligned/exposed_model/ollama.py
aligned/exposed_model/openai.py
aligned/exposed_model/partitioned.py
aligned/exposed_model/sentence_transformer.py
aligned/exposed_model/tests/test_mlflow.py
aligned/exposed_model/tests/test_model.py
aligned/feature_source.py
aligned/feature_store.py
aligned/feature_view/__init__.py
aligned/feature_view/feature_view.py
aligned/feature_view/tests/test_brest_cancer.py
aligned/feature_view/tests/test_brest_cancer_event_timestamp.py
aligned/feature_view/tests/test_check_schema.py
aligned/feature_view/tests/test_custom_source.py
aligned/feature_view/tests/test_hidden_variable.py
aligned/feature_view/tests/test_joined_source.py
aligned/jobs/tests/test_combined_job.py
aligned/jobs/tests/test_derived_job.py
aligned/jobs/tests/test_partial_features.py
aligned/lazy_imports.py
aligned/local/__init__.py
aligned/local/job.py
aligned/local/tests/test_directory_interfaces.py
aligned/local/tests/test_jobs.py
aligned/model_store.py
aligned/polars_to_spark.py
aligned/proxy_api.py
aligned/psql/__init__.py
aligned/psql/jobs.py
aligned/redis/__init__.py
aligned/redis/job.py
aligned/redis/tests/test_redis_job.py
aligned-0.0.136.dist-info/METADATA
aligned-0.0.136.dist-info/WHEEL
aligned-0.0.136.dist-info/entry_points.txt
aligned-0.0.136.dist-info/licenses/LICENSE
aligned-0.0.136.dist-info/RECORD
