Metadata-Version: 2.4
Name: aligned
Version: 0.0.136
Summary: A data management and lineage tool for ML applications.
License: FSL-1.1-ALv2
License-File: LICENSE
Keywords: python,typed,ml,prediction,feature,store,feature-store,mlops,feast,tecton,dbt,data,lineage
Author: Mats E. Mollestad
Author-email: mats@mollestad.no
Requires-Python: >=3.10,<4.0
Classifier: Development Status :: 3 - Alpha
Classifier: Environment :: Web Environment
Classifier: Intended Audience :: Developers
Classifier: License :: OSI Approved :: Apache Software License
Classifier: License :: Other/Proprietary License
Classifier: Operating System :: OS Independent
Classifier: Programming Language :: Python
Classifier: Programming Language :: Python :: 3
Classifier: Programming Language :: Python :: 3.10
Classifier: Programming Language :: Python :: 3.11
Classifier: Programming Language :: Python :: 3.12
Classifier: Programming Language :: Python :: 3.13
Classifier: Programming Language :: Python :: 3.14
Classifier: Topic :: Internet :: WWW/HTTP
Classifier: Topic :: Internet :: WWW/HTTP :: Dynamic Content
Classifier: Topic :: Scientific/Engineering :: Artificial Intelligence
Classifier: Topic :: Software Development
Classifier: Topic :: Software Development :: Libraries
Classifier: Topic :: Software Development :: Libraries :: Application Frameworks
Classifier: Topic :: Software Development :: Libraries :: Python Modules
Provides-Extra: aws
Provides-Extra: azure
Provides-Extra: databricks
Provides-Extra: deltalake
Provides-Extra: image
Provides-Extra: kafka
Provides-Extra: lancedb
Provides-Extra: mlflow
Provides-Extra: ollama
Provides-Extra: openai
Provides-Extra: pandas
Provides-Extra: psql
Provides-Extra: pyiceberg
Provides-Extra: redis
Provides-Extra: sentence-transformers
Provides-Extra: server
Requires-Dist: adlfs (>=2024.4.1,<2025.0.0) ; extra == "azure"
Requires-Dist: aioaws (>=0.12,<0.13) ; extra == "aws"
Requires-Dist: asgi-correlation-id (>=3.0.0,<4.0.0) ; extra == "server"
Requires-Dist: asyncpg (>=0.29.0,<0.30.0) ; extra == "psql"
Requires-Dist: click (>=8.1.3,<9.0.0)
Requires-Dist: connectorx (>=0.3.2,<0.4.0) ; extra == "aws" or extra == "psql"
Requires-Dist: databricks-connect (>15.1.0) ; extra == "databricks"
Requires-Dist: deltalake (>=1.0.0,<2.0.0) ; extra == "deltalake"
Requires-Dist: dill (>=0.3.4,<0.4.0)
Requires-Dist: fastapi (>=0.100.0,<0.101.0) ; extra == "server"
Requires-Dist: httpx (>=0.27.0,<0.28.0)
Requires-Dist: kafka-python (>=2.0.2,<3.0.0) ; extra == "kafka"
Requires-Dist: lancedb (>=0.15.0,<0.16.0) ; extra == "lancedb"
Requires-Dist: mashumaro (>=3.0.1,<4.0.0)
Requires-Dist: mlflow (>=2.11.3,<3.0.0) ; extra == "mlflow"
Requires-Dist: numpy
Requires-Dist: ollama (>=0.1.8,<0.2.0) ; extra == "ollama"
Requires-Dist: openai (>=1.52.0,<2.0.0) ; extra == "openai"
Requires-Dist: pandas (>=2.0.0,<3.0.0) ; extra == "pandas"
Requires-Dist: pillow (>=9.4.0,<10.0.0) ; extra == "image"
Requires-Dist: polars[pyarrow] (>=1.10.0,<2.0.0)
Requires-Dist: psycopg2 (>=2.9.9,<3.0.0) ; extra == "psql"
Requires-Dist: pyarrow (>=17.0.0)
Requires-Dist: pydantic (>=2.0.0,<3.0.0)
Requires-Dist: pyiceberg (>=0.10.0,<0.11.0) ; extra == "pyiceberg"
Requires-Dist: python-dotenv (>=0.21.0,<0.22.0)
Requires-Dist: pytz (>=2024.2,<2025.0)
Requires-Dist: redis (>=4.3.0) ; extra == "redis"
Requires-Dist: sentence-transformers (>=3.2.0,<4.0.0) ; extra == "sentence-transformers"
Requires-Dist: sqlglot (>=22.5.0,<23.0.0) ; extra == "databricks"
Requires-Dist: tiktoken (>=0.8.0,<0.9.0) ; extra == "openai"
Requires-Dist: uvicorn (>=0.17.6,<0.18.0) ; extra == "server"
Project-URL: Homepage, https://github.com/MatsMoll/aligned
Project-URL: Repository, https://github.com/MatsMoll/aligned
